{
  "id": "milton-keynes",
  "name": "Milton Keynes & Bedford",
  "postcode_regex": "^MK\\d",
  "area_column": "area",
  "file_prefix": "milton-keynes-mk-dental",
  "overrides_file": "milton-keynes-dental-manual-overrides.json",
  "core_outward_codes": [
    "MK40",
    "MK45",
    "MK2",
    "MK16",
    "MK18",
    "MK10",
    "MK6",
    "MK9",
    "MK41",
    "MK11",
    "MK17",
    "MK43"
  ],
  "core_segment_prefix": "milton-keynes-core",
  "area_labels": {
    "MK10": "Milton Keynes & Bedford (MK10)",
    "MK11": "Milton Keynes & Bedford (MK11)",
    "MK12": "Milton Keynes & Bedford (MK12)",
    "MK14": "Milton Keynes & Bedford (MK14)",
    "MK15": "Milton Keynes & Bedford (MK15)",
    "MK16": "Milton Keynes & Bedford (MK16)",
    "MK17": "Milton Keynes & Bedford (MK17)",
    "MK18": "Milton Keynes & Bedford (MK18)",
    "MK19": "Milton Keynes & Bedford (MK19)",
    "MK2": "Milton Keynes & Bedford (MK2)",
    "MK3": "Milton Keynes & Bedford (MK3)",
    "MK4": "Milton Keynes & Bedford (MK4)",
    "MK40": "Milton Keynes & Bedford (MK40)",
    "MK41": "Milton Keynes & Bedford (MK41)",
    "MK42": "Milton Keynes & Bedford (MK42)",
    "MK43": "Milton Keynes & Bedford (MK43)",
    "MK44": "Milton Keynes & Bedford (MK44)",
    "MK45": "Milton Keynes & Bedford (MK45)",
    "MK46": "Milton Keynes & Bedford (MK46)",
    "MK5": "Milton Keynes & Bedford (MK5)",
    "MK6": "Milton Keynes & Bedford (MK6)",
    "MK7": "Milton Keynes & Bedford (MK7)",
    "MK8": "Milton Keynes & Bedford (MK8)",
    "MK9": "Milton Keynes & Bedford (MK9)"
  },
  "data_source": "cqc",
  "country": "england"
}
