{
  "id": "york",
  "name": "York",
  "postcode_regex": "^YO\\d",
  "area_column": "area",
  "file_prefix": "york-yo-dental",
  "overrides_file": "york-dental-manual-overrides.json",
  "core_outward_codes": [
    "YO12",
    "YO1",
    "YO24",
    "YO26",
    "YO8",
    "YO25",
    "YO30",
    "YO31",
    "YO17",
    "YO23",
    "YO42",
    "YO7"
  ],
  "core_segment_prefix": "york-core",
  "area_labels": {
    "YO1": "York (YO1)",
    "YO10": "York (YO10)",
    "YO11": "York (YO11)",
    "YO12": "York (YO12)",
    "YO13": "York (YO13)",
    "YO14": "York (YO14)",
    "YO15": "York (YO15)",
    "YO16": "York (YO16)",
    "YO17": "York (YO17)",
    "YO18": "York (YO18)",
    "YO19": "York (YO19)",
    "YO21": "York (YO21)",
    "YO22": "York (YO22)",
    "YO23": "York (YO23)",
    "YO24": "York (YO24)",
    "YO25": "York (YO25)",
    "YO26": "York (YO26)",
    "YO30": "York (YO30)",
    "YO31": "York (YO31)",
    "YO32": "York (YO32)",
    "YO41": "York (YO41)",
    "YO42": "York (YO42)",
    "YO43": "York (YO43)",
    "YO51": "York (YO51)",
    "YO60": "York (YO60)",
    "YO61": "York (YO61)",
    "YO62": "York (YO62)",
    "YO7": "York (YO7)",
    "YO8": "York (YO8)"
  },
  "data_source": "cqc",
  "country": "england"
}
